multicoin/__init__.py
multicoin/main.py
multicoin-0.0.1.dist-info/LICENSE
multicoin-0.0.1.dist-info/METADATA
multicoin-0.0.1.dist-info/WHEEL
multicoin-0.0.1.dist-info/top_level.txt
multicoin-0.0.1.dist-info/RECORD
