Metadata-Version: 2.2
Name: multicoin
Version: 0.0.1
Summary: Multicoin is an ease-of-access Python package packed full of useful tools for developers.
Home-page: https://github.com/TaireruLLC/gitbase
Author: Taireru LLC
Author-email: tairerullc@gmail.com
License: MIT
Classifier: Programming Language :: Python :: 3
Classifier: License :: OSI Approved :: MIT License
Classifier: Operating System :: OS Independent
Requires-Python: >=3.6
License-File: LICENSE
Requires-Dist: requests
Requires-Dist: fancyutil>=0.0.1
Requires-Dist: altcolor>=0.0.5
Dynamic: author
Dynamic: author-email
Dynamic: classifier
Dynamic: description
Dynamic: description-content-type
Dynamic: home-page
Dynamic: license
Dynamic: requires-dist
Dynamic: requires-python
Dynamic: summary
